pygments_minimessage/__init__.py
pygments_minimessage-1.0.0.dist-info/METADATA
pygments_minimessage-1.0.0.dist-info/WHEEL
pygments_minimessage-1.0.0.dist-info/entry_points.txt
pygments_minimessage-1.0.0.dist-info/RECORD
