Metadata-Version: 2.3
Name: pygments-minimessage
Version: 1.0.0
Summary: A Pygments highlighter for the MiniMessage language
License: MIT
Keywords: pygments,lexer,highlighting,adventure
Author: zml
Author-email: zml@kyori.net
Requires-Python: >=3.12
Classifier: Development Status :: 4 - Beta
Classifier: Environment :: Plugins
Requires-Dist: pygments (>=2.19.1,<3.0.0)
Project-URL: Homepage, https://pygments-minimessage.kyori.net/
Project-URL: Repository, https://github.com/KyoriPowered/pygments-minimessage
Project-URL: changelog, https://github.com/KyoriPowered/pygments-minimessage/releases
Project-URL: issues, https://github.com/KyoriPowered/pygments-minimessage/issues
